LUCY/X-5.npy
LUCY/Y-5.npy
LUCY/__init__.py
LUCY/app-tech.py
LUCY/app.py
LUCY/app_chart_model.py
LUCY/data_collection.py
LUCY/data_preprocessing.py
LUCY/eth_price_data_5m.csv
LUCY/hyperparameter.py
LUCY/model_evaluation.py
LUCY/model_training.py
LUCY/scaler-h.pkl
LUCY/setup.py
MyBestFriendLUCY-1.1.3.dist-info/METADATA
MyBestFriendLUCY-1.1.3.dist-info/WHEEL
MyBestFriendLUCY-1.1.3.dist-info/entry_points.txt
MyBestFriendLUCY-1.1.3.dist-info/top_level.txt
MyBestFriendLUCY-1.1.3.dist-info/RECORD
