Metadata-Version: 2.1
Name: MyBestFriendLUCY
Version: 1.1.3
Summary: Ethereum Price Prediction Package for Short-Term Trading
Home-page: https://github.com/yourusername/LUCY-1986-2009-project-ethereum-market-prediction-unit-limit_uncertainty,control_yourself--OurFriendLucy
Author: Isaiah
Author-email: isaiahjpeterson007@gmail.com
Classifier: Programming Language :: Python :: 3
Classifier: License :: OSI Approved :: MIT License
Classifier: Operating System :: OS Independent
Requires-Python: >=3.6
Requires-Dist: tensorflow >=2.0
Requires-Dist: pandas
Requires-Dist: ccxt
Requires-Dist: pandas-ta
Requires-Dist: numpy
Requires-Dist: joblib
Requires-Dist: scikit-learn
Requires-Dist: keras
